flask_apispec/__init__.py
flask_apispec/annotations.py
flask_apispec/apidoc.py
flask_apispec/extension.py
flask_apispec/paths.py
flask_apispec/utils.py
flask_apispec/views.py
flask_apispec/wrapper.py
flask_apispec/__pycache__/__init__.cpython-38.pyc
flask_apispec/__pycache__/annotations.cpython-38.pyc
flask_apispec/__pycache__/apidoc.cpython-38.pyc
flask_apispec/__pycache__/extension.cpython-38.pyc
flask_apispec/__pycache__/paths.cpython-38.pyc
flask_apispec/__pycache__/utils.cpython-38.pyc
flask_apispec/__pycache__/views.cpython-38.pyc
flask_apispec/__pycache__/wrapper.cpython-38.pyc
flask_apispec/static/README.md
flask_apispec/static/absolute-path.js
flask_apispec/static/favicon-16x16.png
flask_apispec/static/favicon-32x32.png
flask_apispec/static/index.html
flask_apispec/static/index.js
flask_apispec/static/oauth2-redirect.html
flask_apispec/static/package.json
flask_apispec/static/swagger-ui-bundle.js
flask_apispec/static/swagger-ui-bundle.js.map
flask_apispec/static/swagger-ui-standalone-preset.js
flask_apispec/static/swagger-ui-standalone-preset.js.map
flask_apispec/static/swagger-ui.css
flask_apispec/static/swagger-ui.css.map
flask_apispec/static/swagger-ui.js
flask_apispec/static/swagger-ui.js.map
flask_apispec/templates/swagger-ui.html
flask_apispec-0.11.4.dist-info/LICENSE
flask_apispec-0.11.4.dist-info/METADATA
flask_apispec-0.11.4.dist-info/WHEEL
flask_apispec-0.11.4.dist-info/top_level.txt
flask_apispec-0.11.4.dist-info/RECORD
