Metadata-Version: 2.1
Name: flask-apispec
Version: 0.11.4
Summary: Build and document REST APIs with Flask and apispec
Home-page: https://github.com/jmcarp/flask-apispec
Author: Joshua Carp
Author-email: jm.carp@gmail.com
License: MIT
Project-URL: Bug Reports, https://github.com/jmcarp/flask-apispec/issues
Project-URL: Changelog, https://flask-apispec.readthedocs.io/en/latest/changelog.html
Keywords: flask marshmallow webargs apispec
Requires-Python: >=3.6
License-File: LICENSE
